{"DATE positive": {"DATE positive": 11}, "FAC positive": {"FAC positive": 2}, "GPE positive": {"GPE positive": 26}, "PRODUCT positive": {"PRODUCT positive": 2}, "MONEY positive": {"MONEY positive": 6}, "PERCENT positive": {"PERCENT positive": 2}, "QUANTITY positive": {"QUANTITY positive": 8}, "DATE negative": {"DATE negative": 26}, "FAC negative": {"FAC negative": 4}, "GPE negative": {"GPE negative": 33}, "PRODUCT negative": {"PRODUCT negative": 1}, "MONEY negative": {"MONEY negative": 4}, "PERCENT negative": {"PERCENT negative": 3}, "QUANTITY negative": {"QUANTITY negative": 5}}
{"DATE positive": {"DATE positive": 7}, "FAC positive": {}, "GPE positive": {"GPE positive": 9}, "PRODUCT positive": {"PRODUCT positive": 3}, "MONEY positive": {"MONEY positive": 6}, "PERCENT positive": {"PERCENT positive": 3}, "QUANTITY positive": {"QUANTITY positive": 5}, "DATE negative": {"DATE negative": 16}, "FAC negative": {}, "GPE negative": {"GPE negative": 15}, "PRODUCT negative": {"PRODUCT negative": 2}, "MONEY negative": {"MONEY negative": 2}, "PERCENT negative": {"PERCENT negative": 4}, "QUANTITY negative": {"QUANTITY negative": 3}}
{"DATE positive": {"DATE positive": 48}, "FAC positive": {"FAC positive": 5}, "GPE positive": {"GPE positive": 73}, "PRODUCT positive": {"PRODUCT positive": 21}, "MONEY positive": {"MONEY positive": 36}, "PERCENT positive": {"PERCENT positive": 21}, "QUANTITY positive": {"QUANTITY positive": 42}, "DATE negative": {"DATE negative": 95}, "FAC negative": {"FAC negative": 15}, "GPE negative": {"GPE negative": 108}, "PRODUCT negative": {"PRODUCT negative": 12}, "MONEY negative": {"MONEY negative": 18}, "PERCENT negative": {"PERCENT negative": 14}, "QUANTITY negative": {"QUANTITY negative": 25}}
{"DATE positive": {"DATE positive": 11}, "FAC positive": {"FAC positive": 2}, "GPE positive": {"GPE positive": 26}, "PRODUCT positive": {"PRODUCT positive": 2}, "MONEY positive": {"MONEY positive": 6}, "PERCENT positive": {"PERCENT positive": 2}, "QUANTITY positive": {"QUANTITY positive": 8}, "DATE negative": {"DATE negative": 26}, "FAC negative": {"FAC negative": 4}, "GPE negative": {"GPE negative": 33}, "PRODUCT negative": {"PRODUCT negative": 1}, "MONEY negative": {"MONEY negative": 4}, "PERCENT negative": {"PERCENT negative": 3}, "QUANTITY negative": {"QUANTITY negative": 5}}
{"DATE positive": {"DATE positive": 11}, "FAC positive": {"FAC positive": 2}, "GPE positive": {"GPE positive": 26}, "PRODUCT positive": {"PRODUCT positive": 2}, "MONEY positive": {"MONEY positive": 6}, "PERCENT positive": {"PERCENT positive": 2}, "QUANTITY positive": {"QUANTITY positive": 8}, "DATE negative": {"DATE negative": 26}, "FAC negative": {"FAC negative": 4}, "GPE negative": {"GPE negative": 33}, "PRODUCT negative": {"PRODUCT negative": 1}, "MONEY negative": {"MONEY negative": 4}, "PERCENT negative": {"PERCENT negative": 3}, "QUANTITY negative": {"QUANTITY negative": 5}}
{"DATE positive": {"DATE negative": 3}, "FAC positive": {"FAC positive": 1}, "GPE positive": {"GPE positive": 6, "GPE negative": 7}, "PRODUCT positive": {}, "MONEY positive": {"MONEY positive": 1, "QUANTITY positive": 1, "MONEY negative": 2}, "PERCENT positive": {"PERCENT positive": 1}, "QUANTITY positive": {"QUANTITY positive": 7}, "DATE negative": {"DATE positive": 1, "DATE negative": 5, "GPE negative": 1}, "FAC negative": {}, "GPE negative": {"DATE negative": 1, "GPE negative": 18}, "PRODUCT negative": {}, "MONEY negative": {"QUANTITY positive": 1, "MONEY negative": 1}, "PERCENT negative": {"PERCENT positive": 2}, "QUANTITY negative": {"QUANTITY positive": 1}}
{"DATE positive": {}, "FAC positive": {}, "GPE positive": {}, "PRODUCT positive": {}, "MONEY positive": {}, "PERCENT positive": {}, "QUANTITY positive": {}, "DATE negative": {}, "FAC negative": {}, "GPE negative": {}, "PRODUCT negative": {}, "MONEY negative": {}, "PERCENT negative": {}, "QUANTITY negative": {}}
{"DATE positive": {"DATE positive": 8, "DATE negative": 4}, "FAC positive": {}, "GPE positive": {"GPE positive": 14, "GPE negative": 12}, "PRODUCT positive": {"PRODUCT positive": 1}, "MONEY positive": {"MONEY positive": 3}, "PERCENT positive": {"PERCENT positive": 1}, "QUANTITY positive": {"QUANTITY positive": 8}, "DATE negative": {"DATE positive": 6, "DATE negative": 20}, "FAC negative": {"GPE negative": 1}, "GPE negative": {"GPE positive": 4, "GPE negative": 29}, "PRODUCT negative": {"PRODUCT positive": 1}, "MONEY negative": {"MONEY positive": 2}, "PERCENT negative": {"PERCENT positive": 1}, "QUANTITY negative": {"QUANTITY positive": 3}}
{"DATE positive": {"DATE positive": 8, "DATE negative": 4}, "DATE negative": {"DATE positive": 6, "DATE negative": 20}, "FAC positive": {}, "FAC negative": {"GPE negative": 1}, "GPE positive": {"GPE positive": 14, "GPE negative": 12}, "GPE negative": {"GPE positive": 4, "GPE negative": 29}, "PRODUCT positive": {"PRODUCT positive": 1}, "PRODUCT negative": {"PRODUCT positive": 1}, "MONEY positive": {"MONEY positive": 3}, "MONEY negative": {"MONEY positive": 2}, "PERCENT positive": {"PERCENT positive": 1}, "PERCENT negative": {"PERCENT positive": 1}, "QUANTITY positive": {"QUANTITY positive": 8}, "QUANTITY negative": {"QUANTITY positive": 3}}
{"DATE positive": {"DATE positive": 8, "DATE negative": 4}, "DATE negative": {"DATE positive": 6, "DATE negative": 20}, "FAC positive": {}, "FAC negative": {"GPE negative": 1}, "GPE positive": {"GPE positive": 14, "GPE negative": 12}, "GPE negative": {"GPE positive": 4, "GPE negative": 29}, "PRODUCT positive": {"PRODUCT positive": 1}, "PRODUCT negative": {"PRODUCT positive": 1}, "MONEY positive": {"MONEY positive": 3}, "MONEY negative": {"MONEY positive": 2}, "PERCENT positive": {"PERCENT positive": 1}, "PERCENT negative": {"PERCENT positive": 1}, "QUANTITY positive": {"QUANTITY positive": 8}, "QUANTITY negative": {"QUANTITY positive": 3}}
{"DATE positive": {"DATE positive": 3, "DATE negative": 1}, "DATE negative": {"DATE positive": 2, "DATE negative": 12}, "FAC positive": {}, "FAC negative": {}, "GPE positive": {"GPE positive": 7, "GPE negative": 6}, "GPE negative": {"GPE positive": 2, "GPE negative": 12}, "PRODUCT positive": {"PRODUCT positive": 2}, "PRODUCT negative": {"PRODUCT positive": 2}, "MONEY positive": {"MONEY positive": 1}, "MONEY negative": {"MONEY positive": 1}, "PERCENT positive": {"PERCENT positive": 1}, "PERCENT negative": {"PERCENT positive": 3}, "QUANTITY positive": {"QUANTITY positive": 1}, "QUANTITY negative": {"QUANTITY positive": 1}}
{"DATE positive": {"DATE positive": 40, "DATE negative": 7}, "DATE negative": {"DATE positive": 21, "DATE negative": 75}, "FAC positive": {"GPE positive": 1, "GPE negative": 1}, "FAC negative": {"FAC negative": 2, "GPE negative": 5}, "GPE positive": {"GPE positive": 44, "GPE negative": 28}, "GPE negative": {"GPE positive": 9, "GPE negative": 92}, "PRODUCT positive": {"PRODUCT positive": 9}, "PRODUCT negative": {"PRODUCT positive": 3, "PRODUCT negative": 2}, "MONEY positive": {"MONEY positive": 29}, "MONEY negative": {"MONEY positive": 11, "MONEY negative": 1}, "PERCENT positive": {"PERCENT positive": 9}, "PERCENT negative": {"PERCENT positive": 6}, "QUANTITY positive": {"QUANTITY positive": 32, "QUANTITY negative": 2}, "QUANTITY negative": {"QUANTITY positive": 10, "QUANTITY negative": 4}}
{"DATE positive": {"DATE positive": 4, "DATE negative": 4}, "DATE negative": {"DATE positive": 2, "DATE negative": 13}, "FAC positive": {}, "FAC negative": {}, "GPE positive": {"GPE positive": 8, "GPE negative": 2}, "GPE negative": {"GPE positive": 3, "GPE negative": 13}, "PRODUCT positive": {"PRODUCT positive": 1}, "PRODUCT negative": {}, "MONEY positive": {"MONEY positive": 4}, "MONEY negative": {"MONEY positive": 2}, "PERCENT positive": {"PERCENT positive": 2}, "PERCENT negative": {"PERCENT positive": 2}, "QUANTITY positive": {"QUANTITY positive": 4}, "QUANTITY negative": {"QUANTITY positive": 1}}
{"DATE positive": {"DATE positive": 12, "DATE negative": 8}, "DATE negative": {"DATE positive": 8, "DATE negative": 33}, "FAC positive": {}, "FAC negative": {"GPE negative": 1}, "GPE positive": {"GPE positive": 22, "GPE negative": 14}, "GPE negative": {"GPE positive": 7, "GPE negative": 42}, "PRODUCT positive": {"PRODUCT positive": 2}, "PRODUCT negative": {"PRODUCT positive": 1}, "MONEY positive": {"MONEY positive": 7}, "MONEY negative": {"MONEY positive": 4}, "PERCENT positive": {"PERCENT positive": 3}, "PERCENT negative": {"PERCENT positive": 3}, "QUANTITY positive": {"QUANTITY positive": 12}, "QUANTITY negative": {"QUANTITY positive": 4}}
{"DATE positive": {"DATE positive": 8, "DATE negative": 4}, "DATE negative": {"DATE positive": 6, "DATE negative": 20}, "FAC positive": {}, "FAC negative": {"GPE negative": 1}, "GPE positive": {"GPE positive": 14, "GPE negative": 12}, "GPE negative": {"GPE positive": 4, "GPE negative": 29}, "PRODUCT positive": {"PRODUCT positive": 1}, "PRODUCT negative": {"PRODUCT positive": 1}, "MONEY positive": {"MONEY positive": 3}, "MONEY negative": {"MONEY positive": 2}, "PERCENT positive": {"PERCENT positive": 1}, "PERCENT negative": {"PERCENT positive": 1}, "QUANTITY positive": {"QUANTITY positive": 8}, "QUANTITY negative": {"QUANTITY positive": 3}}
